traceai_vertexai/__init__.py
traceai_vertexai/_accumulator.py
traceai_vertexai/_instrumentation_status.py
traceai_vertexai/_proxy.py
traceai_vertexai/_wrapper.py
traceai_vertexai/package.py
traceai_vertexai/py.typed
traceai_vertexai/version.py
traceai_vertexai-0.1.9.dist-info/METADATA
traceai_vertexai-0.1.9.dist-info/WHEEL
traceai_vertexai-0.1.9.dist-info/RECORD
